mlc_auth
