Metadata-Version: 2.1
Name: mlc-auth
Version: 0.8.0
Summary: Tools for a easy connection with the MLC authentication portal
Home-page: https://gitlab.com/machine-learning-company/mlc-services/mlc-service-boilerplate
Author: Niels Wijers
Author-email: nielsjlwijers@gmail.com
License: UNKNOWN
Keywords: pip,mlc-services,machine learning company,authentication,mlc-portal
Platform: UNKNOWN
